dicom2gif/__init__.py
dicom2gif/__main__.py
dicom2gif/cine.py
dicom2gif/dicom2gif.py
dicom2gif/read.py
dicom2gif/write.py
dicom2gif-0.0.1.dist-info/METADATA
dicom2gif-0.0.1.dist-info/WHEEL
dicom2gif-0.0.1.dist-info/entry_points.txt
dicom2gif-0.0.1.dist-info/licenses/LICENSE
dicom2gif-0.0.1.dist-info/RECORD
