Metadata-Version: 2.4
Name: dicom2gif
Version: 0.0.1
Summary: A tool to convert DICOM cine movies to GIF format (and others).
Project-URL: Homepage, https://github.com/marcvornehm/dicom2gif
Project-URL: Issues, https://github.com/marcvornehm/dicom2gif/issues
Author-email: Marc Vornehm <marc.vornehm@fau.de>
License-Expression: MIT
License-File: LICENSE
Classifier: Operating System :: OS Independent
Classifier: Programming Language :: Python :: 3
Requires-Python: >=3.10
Requires-Dist: numpy
Requires-Dist: pillow>=7.0.0
Requires-Dist: pydicom
